ganglion/__init__.py
ganglion/_binary_encode.py
ganglion/_digest.py
ganglion/_filesize.py
ganglion/_logging.py
ganglion/api.py
ganglion/api_models.py
ganglion/application_service.py
ganglion/cli.py
ganglion/client.py
ganglion/codec.py
ganglion/common_passwords.py
ganglion/config.py
ganglion/console.py
ganglion/constants.py
ganglion/context.py
ganglion/db.py
ganglion/download_manager.py
ganglion/identity.py
ganglion/middlewares.py
ganglion/models.py
ganglion/msgpack_codec.py
ganglion/packet_decoder.py
ganglion/packets.py
ganglion/password.py
ganglion/regions.py
ganglion/registry.py
ganglion/reserved_slugs.py
ganglion/router.py
ganglion/server.py
ganglion/service.py
ganglion/slugify.py
ganglion/stream.py
ganglion/templates.py
ganglion/timer.py
ganglion/usage.py
ganglion/web_client_service.py
ganglion/websocket_stream.py
ganglion/data/ganglion-local.toml
ganglion/data/static/css/xterm.css
ganglion/data/static/images/background.png
ganglion/data/static/js/textual.js
ganglion/data/templates/404.html
ganglion/data/templates/500.html
ganglion/data/templates/app_index.html
ganglion/data/templates/index.html
ganglion-0.1.1.dist-info/METADATA
ganglion-0.1.1.dist-info/WHEEL
ganglion-0.1.1.dist-info/entry_points.txt
ganglion-0.1.1.dist-info/licenses/LICENSE
ganglion-0.1.1.dist-info/RECORD
