Metadata-Version: 2.4
Name: ganglion
Version: 0.1.1
Summary: Serve multiple Textual apps
License-File: LICENSE
Requires-Python: >=3.13
Requires-Dist: aioconsole>=0.8.1
Requires-Dist: aiohttp-jinja2>=1.6
Requires-Dist: aiohttp[speedups]>=3.11.17
Requires-Dist: aiosqlite>=0.21.0
Requires-Dist: alembic>=1.15.2
Requires-Dist: asyncpg>=0.30.0
Requires-Dist: bcrypt>=4.3.0
Requires-Dist: click>=8.1.8
Requires-Dist: haversine>=2.9.0
Requires-Dist: msgpack>=1.1.0
Requires-Dist: psycopg2-binary>=2.9.10
Requires-Dist: pydantic>=2.11.3
Requires-Dist: rich>=14.0.0
Requires-Dist: sqlalchemy[asyncio]>=2.0.40
Requires-Dist: textual>=3.1.0
Requires-Dist: uvloop>=0.21.0
